README.md
setup.cfg
setup.py
get_nba_data/__init__.py
get_nba_data/advanced_stats.py
get_nba_data/dictionaries.py
get_nba_data/get_table.py
get_nba_data/get_url_parameter.py
get_nba_data/leaders.py
get_nba_data.egg-info/PKG-INFO
get_nba_data.egg-info/SOURCES.txt
get_nba_data.egg-info/dependency_links.txt
get_nba_data.egg-info/not-zip-safe
get_nba_data.egg-info/requires.txt
get_nba_data.egg-info/top_level.txt